django_userlog-0.2.dist-info/DESCRIPTION.rst
django_userlog-0.2.dist-info/METADATA
django_userlog-0.2.dist-info/metadata.json
django_userlog-0.2.dist-info/RECORD
django_userlog-0.2.dist-info/top_level.txt
django_userlog-0.2.dist-info/WHEEL
userlog/__init__.py
userlog/admin.py
userlog/apps.py
userlog/example_settings.py
userlog/example_urls.py
userlog/middleware.py
userlog/realtime.py
userlog/test_settings.py
userlog/tests.py
userlog/util.py
userlog/views.py
userlog/locale/fr/LC_MESSAGES/django.mo
userlog/locale/fr/LC_MESSAGES/django.po
userlog/locale/fr/LC_MESSAGES/djangojs.mo
userlog/locale/fr/LC_MESSAGES/djangojs.po
userlog/static/userlog/js/live.js
userlog/templates/userlog/live.html
userlog/templates/userlog/static.html
